pram2mesa/__init__.py
pram2mesa/make_python_identifier.py
pram2mesa/pram2mesa.py
pram2mesa/rule_writer.py
pram2mesa-0.2.0.dist-info/LICENSE
pram2mesa-0.2.0.dist-info/METADATA
pram2mesa-0.2.0.dist-info/WHEEL
pram2mesa-0.2.0.dist-info/top_level.txt
pram2mesa-0.2.0.dist-info/RECORD
