Metadata-Version: 2.1
Name: pram2mesa
Version: 0.2.0
Summary: Tools for translating PyPRAM's Probabilistic Relational Agent-Based Models to Mesa's Agent-Based Models
Home-page: https://github.com/evankozierok/pram2mesa
Author: Evan Kozierok
Author-email: evan.kozierok@gmail.com
License: UNKNOWN
Platform: UNKNOWN
Classifier: Development Status :: 3 - Alpha
Classifier: Intended Audience :: Science/Research
Classifier: License :: OSI Approved :: MIT License
Classifier: Operating System :: OS Independent
Classifier: Programming Language :: Python :: 3 :: Only
Classifier: Programming Language :: Python :: 3.8
Requires-Python: ~=3.8
Requires-Dist: dill
Requires-Dist: astor
Requires-Dist: autopep8
Requires-Dist: iteround
Requires-Dist: mesa
Requires-Dist: networkx
